hyperchoron/__init__.py
hyperchoron/__main__.py
hyperchoron/dawvert.py
hyperchoron/fastmidi.pyd
hyperchoron/mappings.py
hyperchoron/midi.py
hyperchoron/minecraft.py
hyperchoron/pcm.py
hyperchoron/text.py
hyperchoron/tracker.py
hyperchoron/util.py
hyperchoron/templates/Hyperchoron V2 Header.litematic
hyperchoron/templates/Hyperchoron V2 Looping.litematic
hyperchoron/templates/Hyperchoron V2 Skeleton.litematic
hyperchoron/templates/Hyperchoron V2 Timer.litematic
hyperchoron/templates/Hyperchoron V2 Track.litematic
hyperchoron/templates/Hyperchoron V2 Turn 1.litematic
hyperchoron/templates/Hyperchoron V2 Turn 2.litematic
hyperchoron/templates/Hyperchoron V2 Turn 3.litematic
hyperchoron/templates/Notes.zip
hyperchoron/templates/__init__.py
hyperchoron/templates/soundbank.zip
hyperchoron/templates/__pycache__/__init__.cpython-313.pyc
hyperchoron-1.1.17.dist-info/licenses/LICENSE
hyperchoron-1.1.17.dist-info/METADATA
hyperchoron-1.1.17.dist-info/WHEEL
hyperchoron-1.1.17.dist-info/entry_points.txt
hyperchoron-1.1.17.dist-info/top_level.txt
hyperchoron-1.1.17.dist-info/RECORD
