Metadata-Version: 2.4
Name: hyperchoron
Version: 1.1.17
Author-email: Thomas Xin <thomasxin@gmail.com>
License-Expression: MIT AND (Apache-2.0 OR BSD-2-Clause)
Project-URL: Homepage, https://github.com/thomas-xin/hyperchoron
Project-URL: Issues, https://github.com/thomas-xin/hyperchoron/issues
Classifier: Programming Language :: Python :: 3
Classifier: Programming Language :: Python :: 3.10
Classifier: Programming Language :: Python :: 3.11
Classifier: Programming Language :: Python :: 3.12
Classifier: Programming Language :: Python :: 3.13
Classifier: Programming Language :: Python :: Implementation :: CPython
Classifier: Programming Language :: Rust
Requires-Python: >=3.10
License-File: LICENSE
Requires-Dist: json5>=0.12.0
Requires-Dist: litemapy>=0.11.0b0
Requires-Dist: mcschematic>=11.4.3
Requires-Dist: nbtlib>=2.0.4
Requires-Dist: numpy>=2.2.6
Requires-Dist: orjson>=3.11.3
Requires-Dist: py_midicsv>=4.1.2
Requires-Dist: py7zr>=1.0.0
Requires-Dist: pynbs>=1.1.0
Requires-Dist: scipy>=1.16.1
Requires-Dist: tqdm>=4.67.1
Provides-Extra: pcm
Requires-Dist: audiotsm>=0.1.2; extra == "pcm"
Requires-Dist: audio-separator>=0.34.1; extra == "pcm"
Requires-Dist: imageio-ffmpeg>=0.6.0; extra == "pcm"
Requires-Dist: librosa>=0.11.0; extra == "pcm"
Dynamic: license-file
